cyclemoid_pytorch/__init__.py
cyclemoid_pytorch/cyclemoid.py
cyclemoid_pytorch/easteregg.py
cyclemoid_pytorch-1.1.0.dist-info/LICENSE
cyclemoid_pytorch-1.1.0.dist-info/METADATA
cyclemoid_pytorch-1.1.0.dist-info/WHEEL
cyclemoid_pytorch-1.1.0.dist-info/top_level.txt
cyclemoid_pytorch-1.1.0.dist-info/RECORD
